ai4sci/oml/__init__.py
ai4sci/oml/_online_linear_model.py
ai4sci/oml/_online_model.py
ai4sci.oml-0.2.2.dist-info/LICENSE
ai4sci.oml-0.2.2.dist-info/METADATA
ai4sci.oml-0.2.2.dist-info/WHEEL
ai4sci.oml-0.2.2.dist-info/top_level.txt
ai4sci.oml-0.2.2.dist-info/RECORD
