Metadata-Version: 2.1
Name: ai4sci.oml
Version: 0.2.2
Summary: AI4Science: Efficient data-driven Online Model Learning (OML) / system identification and control
Home-page: https://github.com/haozhg/oml
Author: Hao Zhang
Author-email: haozhang@alumni.princeton.edu
License: MIT
Keywords: machine-learning,AI for Science,data-driven modeling,reduced-order-modeling,dynamical systems,control theory,system identification,online model learning
Classifier: License :: OSI Approved :: MIT License
Classifier: Programming Language :: Python :: 3
Classifier: Programming Language :: Python :: 3.7
Requires-Python: >=3.7
License-File: LICENSE
Requires-Dist: numpy
